hivae/VAE_functions.py
hivae/__init__.py
hivae/graph_new.py
hivae/hivae.py
hivae/impute.py
hivae/loglik_models_missing_normalize.py
hivae/model_HIVAE_factorized.py
hivae/model_HIVAE_inputDropout.py
hivae/parser_arguments.py
hivae/preprocessing.py
hivae/read_functions.py
hivae/utils.py
hivae2-0.13.dist-info/LICENSE
hivae2-0.13.dist-info/METADATA
hivae2-0.13.dist-info/WHEEL
hivae2-0.13.dist-info/top_level.txt
hivae2-0.13.dist-info/RECORD
