Metadata-Version: 2.1
Name: hivae2
Version: 0.13
Summary: HIVAE (Handling incomplete heterogeneous data using VAEs (doi: 10.1016/j.patcog.2020.107501, 2020 and used in Lancet . 2021 (doi: 10.1016/S0140-6736(21)01638-X).Extension of implementations as easy to use Python library/tf2 version (incl. imputation objects for sklearn API) (a.karwath)
Home-page: https://github.com/gkoutos-group/hivae/
Author: Andreas Karwath
Author-email: a.karwath@bham.ac.uk
License: MIT
Platform: UNKNOWN
License-File: LICENSE
Requires-Dist: tensorflow-probability
Requires-Dist: pandas
Requires-Dist: scikit-learn
